rhyolite/__init__.py
rhyolite/config.py
rhyolite/core.py
rhyolite/data.py
rhyolite/dataclasses.py
rhyolite/exceptions.py
rhyolite/py.typed
rhyolite/types.py
rhyolite-1.5.3.dist-info/LICENSE
rhyolite-1.5.3.dist-info/METADATA
rhyolite-1.5.3.dist-info/WHEEL
rhyolite-1.5.3.dist-info/top_level.txt
rhyolite-1.5.3.dist-info/RECORD
